<archimate:ArchimateDiagramModel
    xmlns:xsi="http://www.w3.org/2001/XMLSchema-instance"
    xmlns:archimate="http://www.archimatetool.com/archimate"
    name="Tech:CSS Production"
    id="ea365967"
    viewpoint="13">
  <children
      xsi:type="archimate:DiagramModelArchimateObject"
      id="6a53d317"
      targetConnections="477c2d97 4988593e 556d3a58">
    <sourceConnections
        xsi:type="archimate:DiagramModelArchimateConnection"
        id="990d1055"
        source="6a53d317"
        target="76b37bf7">
      <archimateRelationship
          xsi:type="archimate:AccessRelationship"
          href="AccessRelationship_b320a8a9.xml#b320a8a9"/>
    </sourceConnections>
    <sourceConnections
        xsi:type="archimate:DiagramModelArchimateConnection"
        id="7ba3d5ef"
        source="6a53d317"
        target="1bc7c769">
      <archimateRelationship
          xsi:type="archimate:AccessRelationship"
          href="AccessRelationship_cb2ac746.xml#cb2ac746"/>
    </sourceConnections>
    <sourceConnections
        xsi:type="archimate:DiagramModelArchimateConnection"
        id="72897d99"
        source="6a53d317"
        target="855047f6">
      <archimateRelationship
          xsi:type="archimate:SpecializationRelationship"
          href="SpecializationRelationship_0c4e7592.xml#0c4e7592"/>
    </sourceConnections>
    <bounds
        x="504"
        y="132"
        width="120"
        height="55"/>
    <archimateElement
        xsi:type="archimate:TechnologyService"
        href="TechnologyService_4895a191.xml#4895a191"/>
  </children>
  <children
      xsi:type="archimate:DiagramModelArchimateObject"
      id="76b37bf7"
      targetConnections="990d1055 d9fc4abe">
    <bounds
        x="936"
        y="248"
        width="120"
        height="55"/>
    <archimateElement
        xsi:type="archimate:Artifact"
        href="Artifact_2e495496.xml#2e495496"/>
  </children>
  <children
      xsi:type="archimate:DiagramModelArchimateObject"
      id="1bc7c769"
      targetConnections="7ba3d5ef 80acceea a54298c9">
    <bounds
        x="48"
        y="248"
        width="120"
        height="55"/>
    <archimateElement
        xsi:type="archimate:Artifact"
        href="Artifact_1b1597ae.xml#1b1597ae"/>
  </children>
  <children
      xsi:type="archimate:DiagramModelArchimateObject"
      id="5a1a8b51">
    <sourceConnections
        xsi:type="archimate:DiagramModelArchimateConnection"
        id="477c2d97"
        source="5a1a8b51"
        target="6a53d317">
      <archimateRelationship
          xsi:type="archimate:AssignmentRelationship"
          href="AssignmentRelationship_cdf2228e.xml#cdf2228e"/>
    </sourceConnections>
    <bounds
        x="504"
        y="12"
        width="120"
        height="55"/>
    <archimateElement
        xsi:type="archimate:TechnologyInterface"
        href="TechnologyInterface_86087d1a.xml#86087d1a"/>
  </children>
  <children
      xsi:type="archimate:DiagramModelArchimateObject"
      id="4d190d74">
    <sourceConnections
        xsi:type="archimate:DiagramModelArchimateConnection"
        id="4988593e"
        source="4d190d74"
        target="6a53d317">
      <archimateRelationship
          xsi:type="archimate:ServingRelationship"
          href="ServingRelationship_07a459aa.xml#07a459aa"/>
    </sourceConnections>
    <bounds
        x="252"
        y="248"
        width="120"
        height="55"/>
    <archimateElement
        xsi:type="archimate:TechnologyInterface"
        href="TechnologyInterface_24524f1d.xml#24524f1d"/>
  </children>
  <children
      xsi:type="archimate:DiagramModelArchimateObject"
      id="1eb18a54">
    <sourceConnections
        xsi:type="archimate:DiagramModelArchimateConnection"
        id="556d3a58"
        source="1eb18a54"
        target="6a53d317">
      <archimateRelationship
          xsi:type="archimate:ServingRelationship"
          href="ServingRelationship_8bf4fb5b.xml#8bf4fb5b"/>
    </sourceConnections>
    <bounds
        x="744"
        y="248"
        width="120"
        height="55"/>
    <archimateElement
        xsi:type="archimate:TechnologyInterface"
        href="TechnologyInterface_1fedacc3.xml#1fedacc3"/>
  </children>
  <children
      xsi:type="archimate:DiagramModelArchimateObject"
      id="45c73975"
      targetConnections="e9b65101 3d3018a8">
    <sourceConnections
        xsi:type="archimate:DiagramModelArchimateConnection"
        id="29552383"
        source="45c73975"
        target="8dc35c40">
      <archimateRelationship
          xsi:type="archimate:ServingRelationship"
          href="ServingRelationship_deda3859.xml#deda3859"/>
    </sourceConnections>
    <bounds
        x="264"
        y="372"
        width="120"
        height="55"/>
    <archimateElement
        xsi:type="archimate:Device"
        href="Device_eb8819c1.xml#eb8819c1"/>
  </children>
  <children
      xsi:type="archimate:DiagramModelArchimateObject"
      id="5f431343"
      targetConnections="6a305dce">
    <sourceConnections
        xsi:type="archimate:DiagramModelArchimateConnection"
        id="067a131d"
        source="5f431343"
        target="8dc35c40">
      <archimateRelationship
          xsi:type="archimate:ServingRelationship"
          href="ServingRelationship_ecbead2e.xml#ecbead2e"/>
    </sourceConnections>
    <bounds
        x="744"
        y="372"
        width="120"
        height="55"/>
    <archimateElement
        xsi:type="archimate:Device"
        href="Device_685c4737.xml#685c4737"/>
  </children>
  <children
      xsi:type="archimate:DiagramModelArchimateObject"
      id="8dc35c40"
      targetConnections="067a131d 29552383 ab1a75ed">
    <bounds
        x="504"
        y="372"
        width="120"
        height="55"/>
    <archimateElement
        xsi:type="archimate:Device"
        href="Device_9acf1737.xml#9acf1737"/>
  </children>
  <children
      xsi:type="archimate:DiagramModelArchimateObject"
      id="a6dfa8dd"
      targetConnections="12f47db8">
    <sourceConnections
        xsi:type="archimate:DiagramModelArchimateConnection"
        id="e9b65101"
        source="a6dfa8dd"
        target="45c73975">
      <archimateRelationship
          xsi:type="archimate:ServingRelationship"
          href="ServingRelationship_e59e2771.xml#e59e2771"/>
    </sourceConnections>
    <sourceConnections
        xsi:type="archimate:DiagramModelArchimateConnection"
        id="80acceea"
        source="a6dfa8dd"
        target="1bc7c769">
      <archimateRelationship
          xsi:type="archimate:AccessRelationship"
          href="AccessRelationship_f110d1f7.xml#f110d1f7"/>
    </sourceConnections>
    <bounds
        x="48"
        y="372"
        width="120"
        height="55"/>
    <archimateElement
        xsi:type="archimate:Device"
        href="Device_a5355e5e.xml#a5355e5e"/>
  </children>
  <children
      xsi:type="archimate:DiagramModelArchimateObject"
      id="abef6641"
      targetConnections="a2d36fbb"
      type="1">
    <sourceConnections
        xsi:type="archimate:DiagramModelArchimateConnection"
        id="6a305dce"
        source="abef6641"
        target="5f431343">
      <archimateRelationship
          xsi:type="archimate:SpecializationRelationship"
          href="SpecializationRelationship_10eda1a3.xml#10eda1a3"/>
    </sourceConnections>
    <sourceConnections
        xsi:type="archimate:DiagramModelArchimateConnection"
        id="d9fc4abe"
        source="abef6641"
        target="76b37bf7">
      <archimateRelationship
          xsi:type="archimate:AccessRelationship"
          href="AccessRelationship_57bb5b8f.xml#57bb5b8f"/>
    </sourceConnections>
    <bounds
        x="731"
        y="516"
        width="145"
        height="55"/>
    <archimateElement
        xsi:type="archimate:Device"
        href="Device_eff06e40.xml#eff06e40"/>
  </children>
  <children
      xsi:type="archimate:DiagramModelArchimateObject"
      id="521ff2d4"
      targetConnections="88aac45b"
      type="1">
    <sourceConnections
        xsi:type="archimate:DiagramModelArchimateConnection"
        id="ab1a75ed"
        source="521ff2d4"
        target="8dc35c40">
      <archimateRelationship
          xsi:type="archimate:SpecializationRelationship"
          href="SpecializationRelationship_f9eb9ca0.xml#f9eb9ca0"/>
    </sourceConnections>
    <bounds
        x="491"
        y="516"
        width="145"
        height="55"/>
    <archimateElement
        xsi:type="archimate:Device"
        href="Device_ac7068b2.xml#ac7068b2"/>
  </children>
  <children
      xsi:type="archimate:DiagramModelArchimateObject"
      id="19398dc2"
      targetConnections="8adec8e9"
      type="1">
    <sourceConnections
        xsi:type="archimate:DiagramModelArchimateConnection"
        id="3d3018a8"
        source="19398dc2"
        target="45c73975">
      <archimateRelationship
          xsi:type="archimate:SpecializationRelationship"
          href="SpecializationRelationship_1243bfba.xml#1243bfba"/>
    </sourceConnections>
    <sourceConnections
        xsi:type="archimate:DiagramModelArchimateConnection"
        id="a54298c9"
        source="19398dc2"
        target="1bc7c769">
      <archimateRelationship
          xsi:type="archimate:AccessRelationship"
          href="AccessRelationship_e4940e00.xml#e4940e00"/>
    </sourceConnections>
    <bounds
        x="251"
        y="516"
        width="145"
        height="55"/>
    <archimateElement
        xsi:type="archimate:Device"
        href="Device_22f97800.xml#22f97800"/>
  </children>
  <children
      xsi:type="archimate:DiagramModelArchimateObject"
      id="653a69fd">
    <sourceConnections
        xsi:type="archimate:DiagramModelArchimateConnection"
        id="a2d36fbb"
        source="653a69fd"
        target="abef6641">
      <archimateRelationship
          xsi:type="archimate:AssignmentRelationship"
          href="AssignmentRelationship_8e0e497a.xml#8e0e497a"/>
    </sourceConnections>
    <sourceConnections
        xsi:type="archimate:DiagramModelArchimateConnection"
        id="88aac45b"
        source="653a69fd"
        target="521ff2d4">
      <archimateRelationship
          xsi:type="archimate:AssignmentRelationship"
          href="AssignmentRelationship_d2a169cb.xml#d2a169cb"/>
    </sourceConnections>
    <sourceConnections
        xsi:type="archimate:DiagramModelArchimateConnection"
        id="8adec8e9"
        source="653a69fd"
        target="19398dc2">
      <archimateRelationship
          xsi:type="archimate:AssignmentRelationship"
          href="AssignmentRelationship_11aacc2a.xml#11aacc2a"/>
    </sourceConnections>
    <sourceConnections
        xsi:type="archimate:DiagramModelArchimateConnection"
        id="6d524042"
        source="653a69fd"
        target="288fa5be">
      <archimateRelationship
          xsi:type="archimate:AssignmentRelationship"
          href="AssignmentRelationship_fc6bfc79.xml#fc6bfc79"/>
    </sourceConnections>
    <bounds
        x="504"
        y="648"
        width="120"
        height="55"/>
    <archimateElement
        xsi:type="archimate:Location"
        href="Location_783c23b0.xml#783c23b0"/>
  </children>
  <children
      xsi:type="archimate:DiagramModelArchimateObject"
      id="855047f6"
      targetConnections="72897d99">
    <bounds
        x="504"
        y="248"
        width="120"
        height="55"/>
    <archimateElement
        xsi:type="archimate:TechnologyService"
        href="TechnologyService_8b63e830.xml#8b63e830"/>
  </children>
  <children
      xsi:type="archimate:DiagramModelArchimateObject"
      id="288fa5be"
      targetConnections="6d524042"
      type="1">
    <sourceConnections
        xsi:type="archimate:DiagramModelArchimateConnection"
        id="12f47db8"
        source="288fa5be"
        target="a6dfa8dd">
      <archimateRelationship
          xsi:type="archimate:SpecializationRelationship"
          href="SpecializationRelationship_059f62a6.xml#059f62a6"/>
    </sourceConnections>
    <bounds
        x="48"
        y="516"
        width="120"
        height="55"/>
    <archimateElement
        xsi:type="archimate:Device"
        href="Device_e531f386.xml#e531f386"/>
  </children>
</archimate:ArchimateDiagramModel>
